promptstability/.DS_Store
promptstability/__init__.py
promptstability/core.py
promptstability/data/__init__.py
promptstability/data/example_data.csv
promptstability-0.1.4.dist-info/LICENSE
promptstability-0.1.4.dist-info/METADATA
promptstability-0.1.4.dist-info/WHEEL
promptstability-0.1.4.dist-info/RECORD
