Metadata-Version: 2.1
Name: promptstability
Version: 0.1.4
Summary: Package for generating Prompt Stability Score (PSS). PSS estimates the stability of outcomes resulting from variations in language model prompt specifications.
Home-page: https://github.com/palaiole13/promptstability
License: Apache-2.0
Author: Christopher Barrie, Elli Palaiologou, Petter Törnberg
Requires-Python: >=3.8,<3.11
Classifier: License :: OSI Approved :: Apache Software License
Classifier: Operating System :: OS Independent
Classifier: Programming Language :: Python :: 3
Classifier: Programming Language :: Python :: 3.8
Classifier: Programming Language :: Python :: 3.9
Classifier: Programming Language :: Python :: 3.10
Classifier: Programming Language :: Python :: 3 :: Only
Requires-Dist: matplotlib (>=3.7.2,<4.0.0)
Requires-Dist: numpy (>=1.22.0,<2.0.0)
Requires-Dist: openai (>=1.63.0,<2.0.0)
Requires-Dist: pandas (>=1.5.3,<2.0.0)
Requires-Dist: seaborn (>=0.12.2,<0.13.0)
Requires-Dist: sentence-transformers (>=2.2.2,<3.0.0)
Requires-Dist: sentencepiece (>=0.1.99,<0.2.0)
Requires-Dist: simpledorff (==0.0.2)
Requires-Dist: torch (>=1.13.1,<2.0.0)
Requires-Dist: transformers (>=4.35.0,<5.0.0)
Project-URL: Documentation, https://github.com/palaiole13/promptstability
Project-URL: Repository, https://github.com/palaiole13/promptstability
